Metadata-Version: 1.0
Name: shinkendo
Version: 0.2.1
Summary: A Shinken CLI.
Home-page: http://github.com/sysnove/shinkendo
Author: Guillaume Subiron
Author-email: maethor+pip@subiron.org
License: WTFPL
Platform: UNKNOWN
